mapper/matrix.cpython-310-darwin.so
mapper/filter_function.cpython-310-darwin.so
mapper/multiresolution.cpython-310-darwin.so
mapper/config.cpython-310-darwin.so
mapper/datagraph.cpython-310-darwin.so
mapper/affinities.cpython-310-darwin.so
mapper/flat_cluster.cpython-310-darwin.so
mapper/serialization.cpython-310-darwin.so
mapper/cover.cpython-310-darwin.so
mapper/interface.cpython-310-darwin.so
mapper/cluster_tree.cpython-310-darwin.so
mapper/filter_function_impl.py
mapper/__init__.py
mapper/neighborgraph.cpython-310-darwin.so
mapper/pruning_predicates.cpython-310-darwin.so
mapper/nerve.cpython-310-darwin.so
mapper/mappergraph.cpython-310-darwin.so
mapper/exceptions.cpython-310-darwin.so
mapper/graph.cpython-310-darwin.so
mapper/nngraph.cpython-310-darwin.so
mapper/clustering_scores.cpython-310-darwin.so
mapper/merge_tree.cpython-310-darwin.so
mapper/hierarchical_partition.cpython-310-darwin.so
mapper/py.typed
mapper/data_partition.cpython-310-darwin.so
mapper/distances.cpython-310-darwin.so
mapper/protocols.cpython-310-darwin.so
mapper/_csr_graph.cpython-310-darwin.so
mapper/clustering.cpython-310-darwin.so
mapper_core-0.7.0.dist-info/RECORD
mapper_core-0.7.0.dist-info/WHEEL
mapper_core-0.7.0.dist-info/top_level.txt
mapper_core-0.7.0.dist-info/METADATA
mapper_core-0.7.0.dist-info/licenses/LICENSE
