Metadata-Version: 2.1
Name: mapper-core
Version: 0.7.0
Summary: Core TDA functionality for BluelightAI Cobalt
Home-page: https://cobalt.bluelightai.com
Author: BluelightAI
Author-email: support@bluelightai.com
Classifier: Development Status :: 5 - Production/Stable
Classifier: Operating System :: Unix
Classifier: Operating System :: POSIX
Classifier: Operating System :: Microsoft :: Windows
Classifier: Programming Language :: Python
Classifier: Programming Language :: Python :: 3
Classifier: Programming Language :: Python :: 3 :: Only
Classifier: Programming Language :: Python :: 3.8
Classifier: Programming Language :: Python :: 3.9
Classifier: Programming Language :: Python :: 3.10
Classifier: Programming Language :: Python :: 3.11
Classifier: Programming Language :: Python :: 3.12
Classifier: Programming Language :: Python :: Implementation :: CPython
Classifier: Topic :: Utilities
Classifier: License :: Other/Proprietary License
Requires-Python: >=3.8
License-File: LICENSE
Requires-Dist: numba >=0.55.2
Requires-Dist: numpy
Requires-Dist: pandas >=2
Requires-Dist: pynndescent ~=0.5.13
Requires-Dist: networkx
Requires-Dist: msgpack ~=1.0
Requires-Dist: requests
Requires-Dist: python-dotenv
Requires-Dist: cryptography
Requires-Dist: pynacl
Provides-Extra: dev
Requires-Dist: pytest ~=8.1 ; extra == 'dev'
Requires-Dist: coverage ~=7.6 ; extra == 'dev'
Requires-Dist: pre-commit ~=2.19 ; extra == 'dev'
Requires-Dist: pylint ~=2.13 ; extra == 'dev'
Requires-Dist: tox >=4 ; extra == 'dev'
Requires-Dist: Cython ~=3.0 ; extra == 'dev'
Requires-Dist: pytest-mock ; extra == 'dev'
Provides-Extra: test
Requires-Dist: pytest ~=8.1 ; extra == 'test'
Requires-Dist: tox ~=3.25 ; extra == 'test'
Requires-Dist: rich ~=12.5.1 ; extra == 'test'
Requires-Dist: loguru ~=0.6 ; extra == 'test'
Requires-Dist: py-spy ~=0.3.14 ; extra == 'test'
Requires-Dist: pydantic ~=1.10.2 ; extra == 'test'
Requires-Dist: pytest-mock ; extra == 'test'
